pygamescratch/__init__.py
pygamescratch/doc.py
pygamescratch/pygs.py
pygamescratch/sprite.py
pygamescratch-0.4.9.dist-info/LICENSE
pygamescratch-0.4.9.dist-info/METADATA
pygamescratch-0.4.9.dist-info/WHEEL
pygamescratch-0.4.9.dist-info/top_level.txt
pygamescratch-0.4.9.dist-info/RECORD
